google_sign/__init__.py
google_sign/google_sign.py
google_sign/js2py_sign.py
google_sign-0.0.2.dist-info/LICENSE
google_sign-0.0.2.dist-info/METADATA
google_sign-0.0.2.dist-info/WHEEL
google_sign-0.0.2.dist-info/top_level.txt
google_sign-0.0.2.dist-info/RECORD
