Metadata-Version: 2.1
Name: google-sign
Version: 0.0.2
Summary: Calculate sign string for google translate and baidu translate
Home-page: http://github.com/ffreemt/google-sign
Author: mikeee
License: MIT License
Download-URL: https://github.com/ffreemt/google-sign/archive/v_002.tar.gz
Keywords: machine translation,free,sign
Platform: UNKNOWN
Classifier: Development Status :: 3 - Alpha
Classifier: Intended Audience :: Developers
Classifier: Programming Language :: Python :: 3
Classifier: Programming Language :: Python :: 3.6
Classifier: License :: OSI Approved :: MIT License
Requires-Dist: httpx
Requires-Dist: js2py
Requires-Dist: loguru
